pypara/__init__.py
pypara/currencies.py
pypara/dcc.py
pypara/exchange.py
pypara/monetary.py
pypara/py.typed
pypara/accounting/__init__.py
pypara/accounting/accounts.py
pypara/accounting/generic.py
pypara/accounting/journaling.py
pypara/accounting/ledger.py
pypara/commons/__init__.py
pypara/commons/errors.py
pypara/commons/functional.py
pypara/commons/guid.py
pypara/commons/numbers.py
pypara/commons/zeitgeist.py
pypara-0.1.1.dist-info/LICENSE
pypara-0.1.1.dist-info/METADATA
pypara-0.1.1.dist-info/WHEEL
pypara-0.1.1.dist-info/top_level.txt
pypara-0.1.1.dist-info/RECORD
