Metadata-Version: 2.1
Name: pypara
Version: 0.1.1
Summary: Currencies, Monetary Value Arithmetic/Conversion and Some Type Convenience
Author-email: Vehbi Sinan Tunalioglu <vst@vsthost.com>
License: BSD License
Project-URL: Homepage, https://github.com/vst/pypara
Project-URL: Documentation, https://github.com/vst/pypara#readme
Project-URL: Repository, https://github.com/vst/pypara.git
Project-URL: Changelog, https://github.com/vst/pypara/blob/main/CHANGELOG.md
Keywords: finance
Classifier: Development Status :: 3 - Alpha
Classifier: Intended Audience :: Developers
Classifier: License :: OSI Approved :: BSD License
Classifier: Programming Language :: Python :: 3
Classifier: Programming Language :: Python :: 3.9
Classifier: Programming Language :: Python :: 3.10
Classifier: Programming Language :: Python :: 3.11
Requires-Python: >=3.9
License-File: LICENSE
Requires-Dist: python-dateutil <3.0
Requires-Dist: typing-extensions ; python_version < "3.10"
